{
  "meta": {
    "version": "1.0.0",
    "description": "Prüfungs- und Lebenspfad-Meilensteine mit Tag-Vergabe",
    "schema": "janus7:academy:milestones:v1"
  },
  "milestones": [
    {
      "id": "MILESTONE_YEAR_1_EXAM",
      "name": "Spectatio (Ende Elevium)",
      "evaluationExpr": "state.academy.scoring.eleviumPoints",
      "outcomes": [
        {
          "id": "A_SUMMA_CUM_LAUDE",
          "condition": "value >= 80",
          "grantTags": [
            "prodigy",
            "felenius_favorite"
          ],
          "effectIds": []
        },
        {
          "id": "B_SOLIDUS",
          "condition": "value >= 60",
          "grantTags": [
            "reliable_student"
          ],
          "effectIds": []
        },
        {
          "id": "C_PASSED_BARELY",
          "condition": "value >= 40",
          "grantTags": [
            "underdog"
          ],
          "effectIds": []
        }
      ]
    }
  ]
}